tpt_reading/__init__.py
tpt_reading/base_node.py
tpt_reading/tpt_node_mismatch_exception.py
tpt_reading/tpt_nodes.py
tpt_reading/nodes/__init__.py
tpt_reading/nodes/tpt_data_node.py
tpt_reading/nodes/tpt_node.py
tpt_reading/nodes/tpt_root_node.py
tpt_reading-1.0.dist-info/METADATA
tpt_reading-1.0.dist-info/WHEEL
tpt_reading-1.0.dist-info/top_level.txt
tpt_reading-1.0.dist-info/RECORD
