Metadata-Version: 2.1
Name: tpt-reading
Version: 1.0
Summary: package for template files reading and completion
Home-page: UNKNOWN
Author: Marc MALBERT
Author-email: eldrad-59@hotmail.fr
License: UNKNOWN
Platform: UNKNOWN
Classifier: Programming Language :: Python :: 3
Classifier: Development Status :: 5 - Production/Stable
Classifier: Natural Language :: English
Classifier: Operating System :: OS Independent
